pytorch_mppi/__init__.py
pytorch_mppi/autotune.py
pytorch_mppi/autotune_global.py
pytorch_mppi/autotune_qd.py
pytorch_mppi/mppi.py
pytorch_mppi-0.8.0.dist-info/LICENSE.txt
pytorch_mppi-0.8.0.dist-info/METADATA
pytorch_mppi-0.8.0.dist-info/WHEEL
pytorch_mppi-0.8.0.dist-info/top_level.txt
pytorch_mppi-0.8.0.dist-info/RECORD
