Metadata-Version: 2.1
Name: pytorch_mppi
Version: 0.8.0
Summary: Model Predictive Path Integral (MPPI) implemented in pytorch
Author-email: Sheng Zhong <zhsh@umich.edu>
Maintainer-email: Sheng Zhong <zhsh@umich.edu>
License: Copyright (c) 2023 University of Michigan ARM Lab
Project-URL: Homepage, https://github.com/LemonPi/pytorch_mppi
Project-URL: Bug Reports, https://github.com/LemonPi/pytorch_mppi/issues
Project-URL: Source, https://github.com/LemonPi/pytorch_mppi
Keywords: mppi,pytorch,control,robotics
Classifier: Development Status :: 4 - Beta
Classifier: Intended Audience :: Developers
Classifier: License :: OSI Approved :: MIT License
Classifier: Programming Language :: Python :: 3
Classifier: Programming Language :: Python :: 3 :: Only
Requires-Python: >=3.6
License-File: LICENSE.txt
Requires-Dist: torch
Requires-Dist: numpy
Requires-Dist: arm-pytorch-utilities>=0.4
Provides-Extra: test
Requires-Dist: pytest; extra == "test"
Requires-Dist: gym; extra == "test"
Requires-Dist: pygame; extra == "test"
Requires-Dist: pyglet==1.5.27; extra == "test"
Requires-Dist: window-recorder; extra == "test"
Requires-Dist: cma; extra == "test"
Requires-Dist: ray[tune]; extra == "test"
Requires-Dist: bayesian-optimization; extra == "test"
Requires-Dist: hyperopt; extra == "test"
Provides-Extra: tune
Requires-Dist: cma; extra == "tune"
Requires-Dist: ray[tune]; extra == "tune"
Requires-Dist: bayesian-optimization; extra == "tune"
Requires-Dist: hyperopt; extra == "tune"
